{
	"0": ["一", "二", "三", "四", "五", "六", "七", "八", "九", "十"],
	"1": ["先生", "你", "好", "小姐", "請問", "請", "問", "您", "貴姓", "貴", "姓", "我", "呢", "叫", "什麼", "名字", "王朋", "王", "李友", "李", "是", "老師", "嗎", "不", "學生", "也", "中國人", "中國", "人", "美國人", "美國", "朋友"],
	"2": ["那", "張", "照片", "的", "這", "爸爸", "媽媽", "個", "男孩子", "男", "孩子", "誰", "他", "弟弟", "女孩子", "女", "妹妹", "她", "女兒", "有", "兒子", "沒", "小高", "小", "高", "家", "幾", "哥哥", "兩", "姐姐", "和", "做", "英文", "律師", "都", "大學生", "大學", "醫生", "小張", "張"],
	"3": ["月", "號", "星期", "天", "生日", "生", "日", "今年", "年", "多大", "多", "大", "歲", "請", "吃", "晚飯", "晚", "飯", "吃飯", "怎麼樣", "太⋯了", "謝謝", "喜歡", "還是", "可是", "好", "我們", "點", "鐘", "半", "晚上", "見", "再見", "再", "小白", "白", "現在", "刻", "事", "明天", "忙", "今天", "很", "為什麼", "為", "因為", "還有", "同學", "認識", "小李", "分", "差", "昨天", "明年", "去年", "上個", "下個", "一月", "二月", "三月", "四月", "五月", "六月", "七月", "八月", "九月", "十月", "十一月", "十二月", "星期一", "星期二", "星期三", "星期四", "星期五", "星期六", "星期日", "星期天", "一號", "二號", "三號", "四號", "五號", "六號", "七號", "八號", "九號", "十號", "十一號", "十二號", "十三號", "十四號", "十五號", "十六號", "十七號", "十八號", "十九號", "二十號", "二十一號", "二十二號", "二十三號", "二十四號", "二十五號", "二十六號", "二十七號", "二十八號", "二十九號", "三十號", "三十一號", "上個星期", "這個星期", "下個星期", "上個月", "這個月", "下個月"],
	"4": ["週末", "打球", "打", "球", "看", "電視", "電", "視", "唱歌", "唱", "歌", "跳舞", "跳", "舞", "聽", "音樂", "對", "有時候", "時候", "看書", "書", "電影", "影", "常常", "那", "去", "外國", "請客", "所以", "好久", "久", "不錯", "錯", "想", "覺得", "有意思", "意思", "只", "睡覺", "睡", "算了", "找", "別(的)", "上個週末", "這個週末", "下個週末", "好久不見"],
	"5": ["呀", "進", "快", "進來", "來", "介紹", "一下", "高興", "漂亮", "坐", "在", "哪兒", "工作", "學校", "喝", "點(兒)", "茶", "咖啡", "啤酒", "吧", "要", "杯", "可樂", "可以", "對不起", "給", "水", "玩兒", "圖書館", "瓶", "一起", "聊天兒", "才", "回家", "回"],
	"6": ["給", "打電話", "電話", "話", "餵", "在", "就", "哪", "位", "下午", "時間", "幾", "問題", "要", "開會", "開", "上午", "節", "課", "年級", "考試", "考", "以後", "有空(兒)", "要是", "方便", "到⋯去", "辦公室", "行", "沒問題", "等", "不客氣", "客氣", "幫忙", "別客氣", "別", "中文", "文", "幫", "練習", "說", "啊", "但是", "得", "知道", "回來"],
	"7": ["教", "怎麼", "就", "學", "筆", "難", "快", "哪裡", "第", "預習", "說話", "語法", "容易", "多", "懂", "生詞", "漢字", "有一點兒", "不謝", "平常", "早", "得", "怎麼", "這麼", "半夜", "功課", "朋友", "真", "大家", "早", "開始", "上課", "幫助", "念", "課文", "錄音", "男的", "帥", "複習", "字", "寫", "慢", "寫字"],
	"8": ["篇", "日記", "早上", "起床", "床", "洗澡", "早飯", "一邊⋯一邊⋯", "教室", "上個學期", "這個學期", "下個學期", "發音", "新", "電腦", "腦", "中午", "餐廳", "午飯", "報", "宿舍", "那兒", "⋯的時候", "正在", "以前", "告訴", "已經", "封", "信", "最近", "最", "近", "學期", "除了⋯以外", "專業", "會", "開始", "習慣", "後來", "清楚", "進步", "音樂會", "希望", "能", "用", "笑", "祝", "意文"],
	"9": ["條", "褲子", "號", "中", "貴", "便宜", "付錢", "錢", "這兒", "一共", "多少", "塊", "毛", "分", "百", "找(錢)", "雙", "鞋", "換", "一樣", "雖然", "大小", "合適", "咖啡色", "黑", "不用", "顏色", "買", "東西", "售貨員", "要", "衣服", "件", "襯衫", "黃", "紅", "穿"],
	"11": ["天氣", "比", "下雨", "報上", "預報", "更", "不但⋯而且⋯", "會", "暖和", "一點兒", "約", "公園", "紅葉", "怎麼辦", "錄像", "謝", "上海", "糟糕", "又", "剛才", "這個", "出去", "熱", "舒服", "夏天", "這樣", "涼快", "春天", "冬天", "又⋯又⋯", "冷", "悶", "下次", "次", "最好", "秋天", "台北", "台灣"],
	"10": ["寒假", "飛機", "飛", "機", "票", "(飛)機場", "坐", "公共汽車", "公共", "汽車", "車", "或者", "地鐵", "走", "先", "(車)站", "下車", "然後", "綠", "線", "最後", "藍", "麻歲", "還是", "出租汽車", "出租", "租", "開車", "開", "送", "不過", "讓", "花", "不好意思", "這幾天", "每天", "每", "高速公路", "高速", "公路", "路", "緊張", "自己", "新年", "快", "到", "快樂"],
	"12": ["飯館兒", "服務員", "好像", "位子", "桌子", "點菜", "餃子", "素", "盤", "家常", "豆腐", "肉", "碗", "酸", "辣", "湯", "放", "味精", "渴", "些", "夠", "餓", "上菜", "好", "好吃", "師傅", "中餐", "西餐", "糖", "醋", "魚", "甜", "極了", "紅燒", "牛肉", "賣", "完", "涼拌", "黃瓜", "再", "米飯", "錯"],
	"21": ["借", "盤", "錄音帶", "職員", "把", "學生證", "留", "語言", "實驗室", "樓下", "還", "再", "忘", "帶", "其他的", "證件", "信用卡", "開", "關", "門", "剩", "鐘頭", "可能", "來不及", "本", "圖書館員", "找到", "借書證", "多久", "如果", "過期", "罰", "續借", "必須", "字典"],
	"13": ["上", "中心", "運動", "場", "旁邊", "那麼", "遠", "哪裡", "住", "地方", "離", "近", "就", "活動", "中間", "店", "裡頭", "早知道", "同路", "問路", "過", "中國城", "地圖", "閉", "眼睛", "從", "一直", "往", "南", "過", "路口", "西", "拐", "東", "北", "前", "紅綠燈", "右", "對", "單行道", "左", "面", "日文", "東京"],
	"14": ["呢", "過", "舞會", "女朋友", "表姐", "班", "做飯", "汽水兒", "水果", "果汁", "接", "走路", "說到", "聰明", "用功", "暑期學校", "長得", "可愛", "前年", "屬", "狗", "鼻子", "嘴", "像", "將來", "一定", "臉", "腿", "長", "手指", "以後", "應該", "彈", "鋼琴"],
	"15": ["看病", "病人", "肚子", "疼", "死", "些", "剩菜", "好幾", "廁所", "放", "躺下", "檢查", "壞", "打針", "種", "藥", "片", "小時", "辦法", "想家", "身體", "流", "眼淚", "癢", "過敏", "藥店", "拿", "趕快", "要不然", "越來越", "重", "花", "試", "再說", "生病", "健康保險", "猜"],
	"16": ["同", "參加", "印象", "成", "演", "活", "費", "力氣", "才", "別人", "倆", "後天", "一言為定", "記得", "最後", "想起來", "號碼", "歌劇", "好好兒", "慶祝", "打掃", "房子", "整理", "房間", "紐約", "旅行", "沒關係"],
	"17": ["吵", "準備", "搬", "報紙", "廣告", "附近", "公寓", "英里", "套", "臥室", "廚房", "洗澡間", "客廳", "帶", "傢俱", "房東", "一房一廳", "沙發", "飯桌", "把", "椅子", "單人床", "書桌", "書架", "那裡", "安靜", "非常", "房租", "元", "水電", "費", "押金", "當", "許", "養", "動物"],
	"22": ["郵局", "留學生", "寄", "要", "營業員", "平信", "快信", "越⋯越⋯", "那", "貼", "郵票", "重要", "掛號", "加", "另外", "明信片", "北京", "老是", "首飾", "新鮮", "花", "束", "服務", "訂", "收到", "這裡", "存錢", "剛", "美元", "支票", "它", "人民幣", "銀行"],
	"18": ["當然", "胖", "怕", "簡單", "跑步", "難受", "多⋯啊", "網球", "拍", "籃球", "游泳", "危險", "淹死", "願意", "上大學", "為了", "提高", "聽力", "調", "台", "足球", "賽", "圓", "國際", "美式", "腳", "踢", "手", "抱", "起來-V起來", "被", "壓壞", "擔心", "棒", "特別", "運動服", "受傷", "半天", "看不出來", "輸", "贏"],
	"19": ["放假", "計劃", "各地", "走", "打算", "護照", "辦", "簽證", "訂", "家", "航空", "公司", "減價", "旅行社", "日程", "打折", "九折", "初", "單程", "來回", "不到", "華盛頓", "芝加哥", "轉機", "洛杉磯", "直飛", "漢城", "夜", "香港", "班機", "漲價"],
	"23": ["對面", "春假", "計劃", "父母", "加州", "外公", "外婆", "阿姨", "以為", "親戚", "舊金山", "伯伯", "一家", "老家", "麻州", "城市", "鄉下", "鎮", "人口", "座", "山", "河", "種", "著", "樹", "開", "滿", "美", "聽起來", "風景", "季", "比方說", "滑雪", "歡迎", "生活", "家鄉", "聽說", "首都", "政治", "經濟", "文化", "氣候", "部", "差不多", "分明", "刮風", "的話", "導遊"],
	"20": ["放", "暑假", "探親", "前一天", "收拾", "行李", "出門", "提醒", "停車場", "差不多", "差一點", "找不到", "來到", "服務台", "件", "托運", "皮箱", "隨身", "稱", "超重", "登機證", "起飛", "急", "哭", "長途", "保重", "小心", "一路順風", "表弟", "首都機場", "表哥", "路上", "辛苦", "提", "拿", "瘦", "慣", "公斤", "累壞", "座位", "聊", "爺爺", "奶奶", "孫子", "門口", "叫"]
}
